ml4t/live/AGENT.md
ml4t/live/__init__.py
ml4t/live/_version.py
ml4t/live/engine.py
ml4t/live/protocols.py
ml4t/live/safety.py
ml4t/live/wrappers.py
ml4t/live/brokers/AGENT.md
ml4t/live/brokers/__init__.py
ml4t/live/brokers/alpaca.py
ml4t/live/brokers/ib.py
ml4t/live/feeds/AGENT.md
ml4t/live/feeds/__init__.py
ml4t/live/feeds/aggregator.py
ml4t/live/feeds/alpaca_feed.py
ml4t/live/feeds/crypto_feed.py
ml4t/live/feeds/databento_feed.py
ml4t/live/feeds/ib_feed.py
ml4t/live/feeds/okx_feed.py
ml4t_live-0.1.0a4.dist-info/METADATA
ml4t_live-0.1.0a4.dist-info/WHEEL
ml4t_live-0.1.0a4.dist-info/licenses/LICENSE
ml4t_live-0.1.0a4.dist-info/RECORD
