Metadata-Version: 2.4
Name: ml4t-live
Version: 0.1.0a4
Summary: Live trading platform for ML4T strategies
License-File: LICENSE
Requires-Python: >=3.11
Requires-Dist: alpaca-py>=0.30.0
Requires-Dist: ccxt>=4.5.30
Requires-Dist: httpx>=0.27.0
Requires-Dist: ib-async>=1.0.0
Requires-Dist: ml4t-backtest
Provides-Extra: dev
Requires-Dist: mypy>=1.7; extra == 'dev'
Requires-Dist: pre-commit>=3.0; extra == 'dev'
Requires-Dist: pytest-asyncio>=0.23; extra == 'dev'
Requires-Dist: pytest-cov>=4.1; extra == 'dev'
Requires-Dist: pytest>=8.0; extra == 'dev'
Requires-Dist: ruff>=0.1; extra == 'dev'
